pyrrole/__init__.py
pyrrole/exception.py
pyrrole/pyrrole.py
pyrrole-0.0.7.dist-info/LICENSE.md
pyrrole-0.0.7.dist-info/METADATA
pyrrole-0.0.7.dist-info/WHEEL
pyrrole-0.0.7.dist-info/top_level.txt
pyrrole-0.0.7.dist-info/RECORD
