Metadata-Version: 2.1
Name: pyrrole
Version: 0.0.7
Summary: Role system for Python3
Home-page: https://github.com/MatteoGuadrini/pyrrole
Author: Matteo Guadrini, Giacomo Montagner
Author-email: matteo.guadrini@hotmail.it
Maintainer: Matteo Guadrini, Giacomo Montagner
Maintainer-email: matteo.guadrini@hotmail.it
License: GNU General Public License v3.0
Keywords: pyrrole role roles moose perl
Platform: UNKNOWN
Classifier: Programming Language :: Python :: 3
Classifier: License :: OSI Approved :: GNU General Public License v3 (GPLv3)
Classifier: Operating System :: OS Independent
Requires-Python: >=3.6
License-File: LICENSE.md
